Metadata-Version: 2.1
Name: m3s
Version: 0.5.1
Summary: Multi Spatial Subdivision System - A unified Python package for working with spatial grid systems
Author-email: Nicolas Karasiak <karasiak.nicolas@gmail.com>
License: MIT
Project-URL: Homepage, https://github.com/nkarasiak/m3s
Project-URL: Documentation, https://nkarasiak.github.io/m3s/
Project-URL: Repository, https://github.com/nkarasiak/m3s.git
Project-URL: Bug Tracker, https://github.com/nkarasiak/m3s/issues
Keywords: gis,spatial,grid,geohash,mgrs,h3,quadkey,s2,hierarchical,subdivision,geometry
Classifier: Development Status :: 3 - Alpha
Classifier: Intended Audience :: Developers
Classifier: License :: OSI Approved :: MIT License
Classifier: Operating System :: OS Independent
Classifier: Programming Language :: Python :: 3
Classifier: Programming Language :: Python :: 3.8
Classifier: Programming Language :: Python :: 3.9
Classifier: Programming Language :: Python :: 3.10
Classifier: Programming Language :: Python :: 3.11
Classifier: Programming Language :: Python :: 3.12
Classifier: Topic :: Scientific/Engineering :: GIS
Requires-Python: >=3.9
License-File: LICENSE
Requires-Dist: shapely>=2.0.0
Requires-Dist: pyproj>=3.4.0
Requires-Dist: mgrs>=1.4.0
Requires-Dist: h3>=3.7.0
Requires-Dist: geopandas>=0.13.0
Requires-Dist: s2sphere>=0.2.5
Requires-Dist: psutil>=5.8.0
Provides-Extra: dev
Requires-Dist: pytest>=7.0.0; extra == "dev"
Requires-Dist: pytest-cov>=4.0.0; extra == "dev"
Requires-Dist: black>=22.0.0; extra == "dev"
Requires-Dist: flake8>=5.0.0; extra == "dev"
Requires-Dist: mypy>=1.0.0; extra == "dev"
Requires-Dist: matplotlib>=3.5.0; extra == "dev"
Requires-Dist: pydocstyle>=6.0.0; extra == "dev"
Requires-Dist: flake8-docstrings>=1.6.0; extra == "dev"
Requires-Dist: isort>=5.0.0; extra == "dev"
Requires-Dist: ruff>=0.1.0; extra == "dev"
Requires-Dist: sphinx>=7.0.0; extra == "dev"
Requires-Dist: sphinx-rtd-theme>=2.0.0; extra == "dev"
Requires-Dist: sphinx-autodoc-typehints>=1.20.0; extra == "dev"
Requires-Dist: sphinx-gallery>=0.16.0; extra == "dev"
Requires-Dist: memory-profiler>=0.60.0; extra == "dev"
Provides-Extra: docs
Requires-Dist: sphinx>=7.0.0; extra == "docs"
Requires-Dist: pydata-sphinx-theme>=0.15.0; extra == "docs"
Requires-Dist: sphinx-design>=0.6.0; extra == "docs"
Requires-Dist: sphinx-autodoc-typehints>=1.20.0; extra == "docs"
Requires-Dist: sphinx-gallery>=0.16.0; extra == "docs"
Requires-Dist: memory-profiler>=0.60.0; extra == "docs"
Requires-Dist: matplotlib>=3.5.0; extra == "docs"
Provides-Extra: test
Requires-Dist: pytest>=7.0.0; extra == "test"
Requires-Dist: pytest-cov>=4.0.0; extra == "test"
